README.md
setup.py
miki/__init__.py
miki.egg-info/PKG-INFO
miki.egg-info/SOURCES.txt
miki.egg-info/dependency_links.txt
miki.egg-info/not-zip-safe
miki.egg-info/requires.txt
miki.egg-info/top_level.txt
miki/data/__init__.py
miki/data/dataApi.py
miki/data/dataBcolz.py
miki/data/dataFinance.py
miki/data/dataFunction.py
miki/data/dataGlovar.py
miki/data/dataSchedule.py
miki/data/query.py
miki/trade/__init__.py
miki/trade/context.py
miki/trade/function.py
miki/trade/glovar.py
miki/trade/logger.py
miki/trade/order.py
miki/trade/schedule.py
miki/trade/technical.py
miki/trade/types.py