Metadata-Version: 1.0
Name: miki
Version: 2.0.8
Summary: A Quantitative-research Platform
Home-page: UNKNOWN
Author: chen
Author-email: 435469015@qq.com
License: MIT License
Platform: Independant
